src/__init__.py
odor-0.1.0.dist-info/METADATA
odor-0.1.0.dist-info/WHEEL
odor-0.1.0.dist-info/top_level.txt
odor-0.1.0.dist-info/RECORD
