Metadata-Version: 2.1
Name: odor
Version: 0.1.0
Summary: Factor Evaluation Framework
License: MIT
Classifier: Programming Language :: Python :: 3
Classifier: License :: OSI Approved :: MIT License
Classifier: Operating System :: OS Independent
Requires-Python: >=3.8
